[
    {
        "questionNumber": 1,
        "section": "Икономическа ос (Ляво ↔ Дясно)",
        "questionText": "Ролята на държавата в икономиката",
        "answers": [
            {
                "option": "A) По-голяма намеса и контрол за по добро планиране и справедливост",
                "points": 0
            },
            {
                "option": "B) Умерена намеса за регулиране",
                "points": 1
            },
            {
                "option": "C) Минимална намеса - свободен пазар",
                "points": 2
            }
        ]
    },
    {
        "questionNumber": 2,
        "section": "Икономическа ос (Ляво ↔ Дясно)",
        "questionText": "Данъчна политика",
        "answers": [
            {
                "option": "A) По-високи данъци, за да се финансират социални програми",
                "points": 0
            },
            {
                "option": "B) Балансирани между бизнес и работещи",
                "points": 1
            },
            {
                "option": "C) По-ниски, за да се стимулира бизнеса и потреблението",
                "points": 2
            }
        ]
    },
    {
        "questionNumber": 3,
        "section": "Икономическа ос (Ляво ↔ Дясно)",
        "questionText": "Минимална работна заплата",
        "answers": [
            {
                "option": "A) Да се коригира често, за да отразява разходите за живот",
                "points": 0
            },
            {
                "option": "B) Умерено, с участие на бизнеса и синдикатите",
                "points": 1
            },
            {
                "option": "C) Пазарът да определя колко плащат работодателите",
                "points": 2
            }
        ]
    },
    {
        "questionNumber": 4,
        "section": "Икономическа ос (Ляво ↔ Дясно)",
        "questionText": "Регулации върху бизнеса - околна среда",
        "answers": [
            {
                "option": "A) Повече - за защита на околната среда",
                "points": 0
            },
            {
                "option": "B) Умерени - саморегулрация с държавен надзор",
                "points": 1
            },
            {
                "option": "C) По-малко от сега, за да се стимулира бизнеса",
                "points": 2
            }
        ]
    },
    {
        "questionNumber": 5,
        "section": "Икономическа ос (Ляво ↔ Дясно)",
        "questionText": "Регулации върху бизнеса - работни условия",
        "answers": [
            {
                "option": "A) Повече - за по-добра защита на работниците и служителите",
                "points": 0
            },
            {
                "option": "B) Умерени - саморегулрация с държавен надзор",
                "points": 1
            },
            {
                "option": "C) По-малко от сега, за да се стимулира бизнеса",
                "points": 2
            }
        ]
    },
    {
        "questionNumber": 6,
        "section": "Икономическа ос (Ляво ↔ Дясно)",
        "questionText": "Приватизация",
        "answers": [
            {
                "option": "A) Приватизацията беше вредна",
                "points": 0
            },
            {
                "option": "B) Зависи кои индустрии и предприятия, и как се управляват",
                "points": 1
            },
            {
                "option": "C) Полезна, защото държавата не може да управлява ефективно бизнес",
                "points": 2
            }
        ]
    },
    {
        "questionNumber": 7,
        "section": "Икономическа ос (Ляво ↔ Дясно)",
        "questionText": "Социални помощи",
        "answers": [
            {
                "option": "A) Трябва да се увеличат, за да се помогне на най-уязвимите",
                "points": 0
            },
            {
                "option": "B) Запазване - контрол на злоупотребите, но с достатъчно за нуждаещите се",
                "points": 1
            },
            {
                "option": "C) Ограничаване - всеки би трябвало да се грижи за себе си",
                "points": 2
            }
        ]
    },
    {
        "questionNumber": 8,
        "section": "Икономическа ос (Ляво ↔ Дясно)",
        "questionText": "Здравеопазване",
        "answers": [
            {
                "option": "A) Държавно - държавата трябва да осигури основно здравеопазване за всички",
                "points": 0
            },
            {
                "option": "B) Смесено - комбинация от държавно и допълващо частно здравеопазване",
                "points": 1
            },
            {
                "option": "C) Частно - държавата не може да управлява ефективно здравеопазването",
                "points": 2
            }
        ]
    },
    {
        "questionNumber": 9,
        "section": "Икономическа ос (Ляво ↔ Дясно)",
        "questionText": "Пенсионна система",
        "answers": [
            {
                "option": "A) Само държавна гаранция - държавата трябва да гарантира пенсия за всички",
                "points": 0
            },
            {
                "option": "B) Смесена - държавна основа с допълнителни частни фондове",
                "points": 1
            },
            {
                "option": "C) Само частни фондове на пазарен принцип",
                "points": 2
            }
        ]
    },
    {
        "questionNumber": 10,
        "section": "Икономическа ос (Ляво ↔ Дясно)",
        "questionText": "Неравенства",
        "answers": [
            {
                "option": "A) Активно намаляване на неравенствата чрез данъци и социални програми",
                "points": 0
            },
            {
                "option": "B) Умерено, с регулиране на специфични групи от хора",
                "points": 1
            },
            {
                "option": "C) Естествени - без намеса, защото това е резултат от различни способности и усилия",
                "points": 2
            }
        ]
    },
    {
        "questionNumber": 11,
        "section": "Икономическа ос (Ляво ↔ Дясно)",
        "questionText": "Свободна търговия",
        "answers": [
            {
                "option": "A) Контрол на търговията, за да се защити местната икономика и работни места",
                "points": 0
            },
            {
                "option": "B) Регулация - с цел защита на определени сектори и работни места",
                "points": 1
            },
            {
                "option": "C) Свободен пазар, основан на конкурентни предимства",
                "points": 2
            }
        ]
    },
    {
        "questionNumber": 12,
        "section": "Социално-културна ос (Прогресивно ↔ Консервативно)",
        "questionText": "Международна миграция",
        "answers": [
            {
                "option": "A) Отворена - всеки трябва да има право да живее и работи където пожелае",
                "points": 0
            },
            {
                "option": "B) Балансирана - с определени квоти и изисквания за интеграция",
                "points": 1
            },
            {
                "option": "C) Строга - ограничаване на миграцията и строги изисквания за влизане",
                "points": 2
            }
        ]
    },
    {
        "questionNumber": 13,
        "section": "Социално-културна ос (Прогресивно ↔ Консервативно)",
        "questionText": "Традиционни ценности",
        "answers": [
            {
                "option": "A) Трябва промяна и модернизация - адаптиране към съвременните световни идеи",
                "points": 0
            },
            {
                "option": "B) Баланс - модерните ценности са важни, но трябва да се запазят и някои традиционни",
                "points": 1
            },
            {
                "option": "C) Запазване и защита на традиционните ценности, и избягване на промяната",
                "points": 2
            }
        ]
    },
    {
        "questionNumber": 14,
        "section": "Социално-културна ос (Прогресивно ↔ Консервативно)",
        "questionText": "Религия",
        "answers": [
            {
                "option": "A) Отделена от държавата и образованието",
                "points": 0
            },
            {
                "option": "B) Културна роля, но не и политическа",
                "points": 1
            },
            {
                "option": "C) Важна част от изграждането на ценности и морал",
                "points": 2
            }
        ]
    },
    {
        "questionNumber": 15,
        "section": "Социално-културна ос (Прогресивно ↔ Консервативно)",
        "questionText": "Права на малцинства",
        "answers": [
            {
                "option": "A) Разширяване, защото те са неравноправни и дискриминирани",
                "points": 0
            },
            {
                "option": "B) Гарантиране - защита на техните права и равенство пред закона",
                "points": 1
            },
            {
                "option": "C) Вече имат достатъчно права",
                "points": 2
            }
        ]
    },
    {
        "questionNumber": 16,
        "section": "Социално-културна ос (Прогресивно ↔ Консервативно)",
        "questionText": "Медии",
        "answers": [
            {
                "option": "A) Минимална намеса и контрол, дори с риск от фалшиви новини",
                "points": 0
            },
            {
                "option": "B) Публичен контрол за предотвратяване на фалшиви новини и пропаганда",
                "points": 1
            },
            {
                "option": "C) Строг държавен контрол за предотвратяване на фалшиви новини и пропаганда",
                "points": 2
            }
        ]
    },
    {
        "questionNumber": 17,
        "section": "Социално-културна ос (Прогресивно ↔ Консервативно)",
        "questionText": "Образование",
        "answers": [
            {
                "option": "A) Модерни ценности - адаптирани към съвременните световни идеи",
                "points": 0
            },
            {
                "option": "B) Балансирана - с определени квоти и изисквания за интеграция",
                "points": 1
            },
            {
                "option": "C) Сегашните методи и ценности са добри, но не се прилагат достатъчно",
                "points": 2
            }
        ]
    },
    {
        "questionNumber": 18,
        "section": "Социално-културна ос (Прогресивно ↔ Консервативно)",
        "questionText": "Сигурност",
        "answers": [
            {
                "option": "A) По-малко правомощия на правораздаващите органи, за да се гарантират гражданските права",
                "points": 0
            },
            {
                "option": "B) Умерени правомощия за защита на гражданите, но с гаранции за правата им",
                "points": 1
            },
            {
                "option": "C) По-силни правомощия за защита на гражданите, дори с риск за някои права",
                "points": 2
            }
        ]
    },
    {
        "questionNumber": 19,
        "section": "Социално-културна ос (Прогресивно ↔ Консервативно)",
        "questionText": "ЛГБТ+ права",
        "answers": [
            {
                "option": "A) Разширяване - тези общности сега са неравнопоставени и дискриминирани",
                "points": 0
            },
            {
                "option": "B) Запазване - вече имат достатъчно права",
                "points": 1
            },
            {
                "option": "C) Ограничаване - техните ценности и начин на живот не трябва да се насърчават",
                "points": 2
            }
        ]
    },
    {
        "questionNumber": 20,
        "section": "Социално-културна ос (Прогресивно ↔ Консервативно)",
        "questionText": "Екология",
        "answers": [
            {
                "option": "A) Строги мерки за опазване на околната среда, дори с риск за икономическия растеж",
                "points": 0
            },
            {
                "option": "B) Баланс - между опазване на околната среда и икономическия растеж",
                "points": 1
            },
            {
                "option": "C) Икономика първо - приоритет на икономическия растеж пред опазването на околната среда",
                "points": 2
            }
        ]
    },
    {
        "questionNumber": 21,
        "section": "Социално-културна ос (Прогресивно ↔ Консервативно)",
        "questionText": "Личен живот",
        "answers": [
            {
                "option": "A) Минимална намеса - максимална свобода за личен живот и избори",
                "points": 0
            },
            {
                "option": "B) Умерена намеса - баланс между личната свобода и обществените интереси",
                "points": 1
            },
            {
                "option": "C) По-голяма намеса - приоритет на обществените интереси пред личната свобода",
                "points": 2
            }
        ]
    }
]
